LICENSE.txt
README.rst
setup.py
rbxexecutions/__init__.py
rbxexecutions/api/__init__.py
rbxexecutions/discordbot/__init__.py
rbxexecutions/discordbot/cogs/__init__.py
rbxexecutions/discordbot/cogs/commands.py
rbxexecutions/discordbot/cogs/status.py
robloxapi1/__init__.py
robloxapi1.egg-info/PKG-INFO
robloxapi1.egg-info/SOURCES.txt
robloxapi1.egg-info/dependency_links.txt
robloxapi1.egg-info/requires.txt
robloxapi1.egg-info/top_level.txt