Metadata-Version: 2.1
Name: robloxapi1
Version: 0
Summary: pip install roblox
Home-page: UNKNOWN
Author: MaGiXx
License: MIT
Keywords: roblox api
Platform: UNKNOWN
License-File: LICENSE.txt
